cfit/__init__.py
cfit/cli.py
cfit/core.py
cfit/utils.py
cfit-0.1.0.post1.dist-info/METADATA
cfit-0.1.0.post1.dist-info/WHEEL
cfit-0.1.0.post1.dist-info/entry_points.txt
cfit-0.1.0.post1.dist-info/RECORD
