Metadata-Version: 2.1
Name: cfit
Version: 0.1.0.post1
Summary: A tool to estimate GPU memory requirements
License: MIT
Author: jeonsworld
Author-email: jeonsworld@gmail.com
Requires-Python: >=3.7,<4.0
Classifier: License :: OSI Approved :: MIT License
Classifier: Programming Language :: Python :: 3
Classifier: Programming Language :: Python :: 3.7
Classifier: Programming Language :: Python :: 3.8
Classifier: Programming Language :: Python :: 3.9
Classifier: Programming Language :: Python :: 3.10
Classifier: Programming Language :: Python :: 3.11
Classifier: Programming Language :: Python :: 3.12
Provides-Extra: test
Requires-Dist: huggingface-hub (>=0.23.0,<0.24.0)
